unirio/__init__.py
unirio/api/__init__.py
unirio/api/exceptions.py
unirio/api/request.py
unirio/api/result.py
unirio_api-1.1.1.dist-info/DESCRIPTION.rst
unirio_api-1.1.1.dist-info/METADATA
unirio_api-1.1.1.dist-info/metadata.json
unirio_api-1.1.1.dist-info/pbr.json
unirio_api-1.1.1.dist-info/RECORD
unirio_api-1.1.1.dist-info/top_level.txt
unirio_api-1.1.1.dist-info/WHEEL
