Metadata-Version: 2.0
Name: unirio-api
Version: 1.1.1
Summary: Client package for the RESTful api provided by the Universidade Federal do Estado do Rio de Janeiro (UNIRIO)
Home-page: https://github.com/unirio-dtic/api_client
Author: Diogo Magalhães Martins
Author-email: magalhaesmartins@icloud.com
License: GPLv2
Keywords: unirio api rest sie development
Platform: UNKNOWN
Classifier: Development Status :: 5 - Production/Stable
Classifier: Intended Audience :: Developers
Classifier: Intended Audience :: Education
Classifier: License :: Public Domain
Classifier: Natural Language :: English
Classifier: Operating System :: OS Independent
Classifier: Programming Language :: Python :: 2.7
Classifier: Programming Language :: Python :: 3
Classifier: Programming Language :: Python :: 3.3
Classifier: Programming Language :: Python :: 3.4
Classifier: Programming Language :: Python :: 3.5
Classifier: Topic :: Software Development :: Libraries
Classifier: Topic :: Internet :: WWW/HTTP
Classifier: Topic :: Internet :: WWW/HTTP :: Dynamic Content
Requires-Dist: requests (>=2.7.0)
Requires-Dist: enum34 (>=1.1.6)
Requires-Dist: codecov
